par_batch_map/__init__.py
par_batch_map/batch_map.py
par_batch_map/mongodb_example.py
par_batch_map/utils.py
par_batch_map-0.0.1.post2.dist-info/LICENSE
par_batch_map-0.0.1.post2.dist-info/METADATA
par_batch_map-0.0.1.post2.dist-info/WHEEL
par_batch_map-0.0.1.post2.dist-info/top_level.txt
par_batch_map-0.0.1.post2.dist-info/RECORD
