Metadata-Version: 2.1
Name: par-batch-map
Version: 0.0.1.post2
Summary: Package for parallel batch processing of iterators
Home-page: https://git.icm.edu.pl/krutk/parallel_batch
Author: Krzysztof Rutkowski
Author-email: krutk@icm.edu.pl
License: UNKNOWN
Platform: UNKNOWN
Classifier: Programming Language :: Python :: 3
Classifier: License :: OSI Approved :: MIT License
Classifier: Operating System :: Unix
Requires-Python: >=3.8
Requires-Dist: pymongo (==3.9.0)
Requires-Dist: haversine (==2.1.2)
Requires-Dist: numpy (==1.17.4)
Requires-Dist: Shapely (==1.6.4.post2)
